pydepguardnext/.sigstore
pydepguardnext/.sigstore.asc
pydepguardnext/__init__.py
pydepguardnext/__main__.py
pydepguardnext/api/__init__.py
pydepguardnext/api/errors.py
pydepguardnext/api/auth/guard.py
pydepguardnext/api/compat/__init__.py
pydepguardnext/api/compat/validator.py
pydepguardnext/api/deps/__init__.py
pydepguardnext/api/deps/enrich.py
pydepguardnext/api/deps/lockfile.py
pydepguardnext/api/deps/name.py
pydepguardnext/api/deps/version.py
pydepguardnext/api/deps/walker.py
pydepguardnext/api/factories/__init__.py
pydepguardnext/api/factories/mappingproxy_ovr.py
pydepguardnext/api/flags/flag.py
pydepguardnext/api/install/__init__.py
pydepguardnext/api/install/pip.py
pydepguardnext/api/install/parser/__init__.py
pydepguardnext/api/install/parser/cli_install.py
pydepguardnext/api/install/parser/common.py
pydepguardnext/api/install/parser/json.py
pydepguardnext/api/install/parser/magic.py
pydepguardnext/api/install/parser/pipfile.py
pydepguardnext/api/install/parser/poetry.py
pydepguardnext/api/install/parser/req.py
pydepguardnext/api/install/parser/setupcfg.py
pydepguardnext/api/install/parser/stdin.py
pydepguardnext/api/jit/__init__.py
pydepguardnext/api/jit/jit.py
pydepguardnext/api/lockfile/__init__.py
pydepguardnext/api/lockfile/manager.py
pydepguardnext/api/log/__init__.py
pydepguardnext/api/log/logit.py
pydepguardnext/api/net/entropy_utils.py
pydepguardnext/api/net/genkey.py
pydepguardnext/api/net/key_utils.py
pydepguardnext/api/net/keyclasses.py
pydepguardnext/api/net/memoryhandler.py
pydepguardnext/api/net/net_errors.py
pydepguardnext/api/permissions/pal.py
pydepguardnext/api/policy/__init__.py
pydepguardnext/api/policy/context.py
pydepguardnext/api/run/__init__.py
pydepguardnext/api/run/lambda_runner.py
pydepguardnext/api/runtime/__init__.py
pydepguardnext/api/runtime/airjail.py
pydepguardnext/api/runtime/guard.py
pydepguardnext/api/runtime/importer.py
pydepguardnext/api/runtime/mutator.py
pydepguardnext/api/runtime/no_guard.py
pydepguardnext-2.0.8.dist-info/licenses/LICENSE.md
pydepguardnext-2.0.8.dist-info/METADATA
pydepguardnext-2.0.8.dist-info/WHEEL
pydepguardnext-2.0.8.dist-info/top_level.txt
pydepguardnext-2.0.8.dist-info/RECORD
